deepdirect/__init__.py
deepdirect/model.py
deepdirect/mutator.py
deepdirect/weights/model_d_weights.h5
deepdirect/weights/model_i_weights.h5
deepdirect-0.2.5.dist-info/LICENSE
deepdirect-0.2.5.dist-info/METADATA
deepdirect-0.2.5.dist-info/WHEEL
deepdirect-0.2.5.dist-info/top_level.txt
deepdirect-0.2.5.dist-info/RECORD
