Metadata-Version: 2.1
Name: deepdirect
Version: 0.2.5
Summary: In silico approach to generate mutations for protein complexes towards a specified direction (increase/decrease) in binding affinity.
Home-page: https://github.com/Jappy0/deepdirect
Author: Tian Lan and Penagyao Ping
Author-email: lantian000@outlook.com, ping.pengyao@gmail.com
Classifier: Programming Language :: Python :: 3
Classifier: License :: OSI Approved :: GNU General Public License v3 (GPLv3)
Classifier: Operating System :: OS Independent
License-File: LICENSE
Requires-Dist: tensorflow ==2.12.0
Requires-Dist: Keras ==2.12.0
